ebookrack/__init__.py
ebookrack/catalogue.py
ebookrack/library.py
ebookrack/shelf.py
ebookrack/calibre/__init__.py
ebookrack/calibre/library.py
ebookrack/calibre/metadata.py
ebookrack-0.3.1.dist-info/WHEEL
ebookrack-0.3.1.dist-info/METADATA
ebookrack-0.3.1.dist-info/RECORD
