Metadata-Version: 2.1
Name: ebookrack
Version: 0.3.1
Summary: library for managing a personal e-book library
Author-email: JA Viljoen <ebookrack@javiljoen.net>
Requires-Python: ~=3.8
Classifier: Development Status :: 3 - Alpha
Classifier: Environment :: Console
Classifier: Intended Audience :: End Users/Desktop
Classifier: License :: OSI Approved :: European Union Public Licence 1.2 (EUPL 1.2)
Classifier: Operating System :: POSIX
Classifier: Topic :: Text Processing :: Markup :: XML
Classifier: Topic :: Utilities
Requires-Dist: pytest ~=7.2.1 ; extra == "test"
Project-URL: Repository, https://git.sr.ht/~javiljoen/ebookrack-python
Provides-Extra: test
